pyvpsq/__init__.py
pyvpsq/buffer.py
pyvpsq/connection.py
pyvpsq/constants.py
pyvpsq/exceptions.py
pyvpsq/logger.py
pyvpsq/packet.py
pyvpsq/principalserver.py
pyvpsq/server.py
pyvpsq-0.2.1.dist-info/licenses/LICENSE
pyvpsq-0.2.1.dist-info/METADATA
pyvpsq-0.2.1.dist-info/WHEEL
pyvpsq-0.2.1.dist-info/top_level.txt
pyvpsq-0.2.1.dist-info/RECORD
