Metadata-Version: 2.4
Name: pyvpsq
Version: 0.2.1
Summary: Simple Python library for querying Valve's principal servers
Home-page: https://github.com/cetteup/pyvpsq
Author: cetteup
Author-email: me@cetteup.com
License: MIT
Project-URL: Bug Tracker, https://github.com/cetteup/pyvpsq/issues
Classifier: Development Status :: 3 - Alpha
Classifier: Intended Audience :: Developers
Classifier: License :: OSI Approved :: MIT License
Classifier: Operating System :: OS Independent
Classifier: Programming Language :: Python :: 3
Requires-Python: >=3.10
License-File: LICENSE
Dynamic: license-file
